jupyter_stack_trace/__init__.py
jupyter_stack_trace/_version.py
jupyter_stack_trace-0.1.7.data/data/share/jupyter/labextensions/jupyter-stack-trace/package.json
jupyter_stack_trace-0.1.7.data/data/share/jupyter/labextensions/jupyter-stack-trace/schemas/jupyter-stack-trace/package.json.orig
jupyter_stack_trace-0.1.7.data/data/share/jupyter/labextensions/jupyter-stack-trace/schemas/jupyter-stack-trace/plugin.json
jupyter_stack_trace-0.1.7.data/data/share/jupyter/labextensions/jupyter-stack-trace/static/462.7e751f5dea27c0444c64.js
jupyter_stack_trace-0.1.7.data/data/share/jupyter/labextensions/jupyter-stack-trace/static/747.9ea6e19c44d9cf54ab7c.js
jupyter_stack_trace-0.1.7.data/data/share/jupyter/labextensions/jupyter-stack-trace/static/remoteEntry.13d12e08483a9607eeb6.js
jupyter_stack_trace-0.1.7.data/data/share/jupyter/labextensions/jupyter-stack-trace/static/style.js
jupyter_stack_trace-0.1.7.data/data/share/jupyter/labextensions/jupyter-stack-trace/static/third-party-licenses.json
jupyter_stack_trace-0.1.7.data/data/share/jupyter/labextensions/jupyter-stack-trace/install.json
jupyter_stack_trace-0.1.7.dist-info/METADATA
jupyter_stack_trace-0.1.7.dist-info/WHEEL
jupyter_stack_trace-0.1.7.dist-info/licenses/LICENSE
jupyter_stack_trace-0.1.7.dist-info/RECORD
