Metadata-Version: 2.3
Name: jupyter_stack_trace
Version: 0.1.7
Dynamic: Keywords
Summary: A JupyterLab extension to jump to the line in the file of the stack trace.
Project-URL: Homepage, https://github.com/teticio/jupyter-stack-trace
Project-URL: Bug Tracker, https://github.com/teticio/jupyter-stack-trace/issues
Project-URL: Repository, https://github.com/teticio/jupyter-stack-trace.git
Author-email: Robert Dargavel Smith <teticio@gmail.com>
License: BSD 3-Clause License
License-File: LICENSE
Classifier: Framework :: Jupyter
Classifier: Framework :: Jupyter :: JupyterLab
Classifier: Framework :: Jupyter :: JupyterLab :: 4
Classifier: Framework :: Jupyter :: JupyterLab :: Extensions
Classifier: Framework :: Jupyter :: JupyterLab :: Extensions :: Prebuilt
Classifier: License :: OSI Approved :: BSD License
Classifier: Programming Language :: Python
Classifier: Programming Language :: Python :: 3
Classifier: Programming Language :: Python :: 3.8
Classifier: Programming Language :: Python :: 3.9
Classifier: Programming Language :: Python :: 3.10
Classifier: Programming Language :: Python :: 3.11
Requires-Python: >=3.8
